[
  {
    "model": "core.auditlog",
    "pk": 1001,
    "fields": {
      "event_id": "d68a0f2b-8f20-4fea-99de-3f18d4026f6d",
      "actor_user": null,
      "action": "created",
      "target_table": "finance.FinanceStatus",
      "target_id": "19",
      "before": {},
      "after": {
        "id": 19,
        "student": 27,
        "academic_year": 2025,
        "trimester": 1,
        "total_due": "120000.00",
        "total_paid": "90000.00",
        "status": "partial",
        "clearance_status": "cleared_for_registration"
      },
      "request_id": "",
      "request_path": "",
      "request_method": "",
      "request_status": null,
      "ip_address": "",
      "user_agent": "",
      "metadata": {},
      "previous_hash": "2b49839c8df4f71e422fc40aa00964f7f8a68fbf9f990e41ebdb1bbd3082a506",
      "integrity_hash": "c40695ce219a1e00a2449b4f9423276eb09af88c6189681e0256ec003a655559",
      "created_at": "2026-03-19T07:17:03.311Z"
    }
  },
  {
    "model": "core.auditlog",
    "pk": 1002,
    "fields": {
      "event_id": "1a05f0a5-cba6-48fc-bcc1-ea936cfddb28",
      "actor_user": null,
      "action": "updated",
      "target_table": "users.Student",
      "target_id": "27",
      "before": {},
      "after": {
        "user": 27,
        "programme": 1,
        "year": 1,
        "trimester": 1,
        "trimester_label": "Year 1, Trimester 1",
        "admission_date": "2026-03-12",
        "current_status": "active",
        "stars": 0
      },
      "request_id": "",
      "request_path": "",
      "request_method": "",
      "request_status": null,
      "ip_address": "",
      "user_agent": "",
      "metadata": {},
      "previous_hash": "c40695ce219a1e00a2449b4f9423276eb09af88c6189681e0256ec003a655559",
      "integrity_hash": "5e7ebe2fe10547e4b32b0eee0e48456de29e580da6f249f314d56eee23841d0c",
      "created_at": "2026-03-19T07:17:03.312Z"
    }
  },
  {
    "model": "core.auditlog",
    "pk": 1003,
    "fields": {
      "event_id": "4995347c-9955-481a-8928-c22301922ae5",
      "actor_user": null,
      "action": "created",
      "target_table": "learning.Registration",
      "target_id": "51",
      "before": {},
      "after": {
        "id": 51,
        "student": 29,
        "unit": 1,
        "academic_year": 2025,
        "trimester": 1,
        "status": "approved",
        "approved_by": null,
        "approved_at": "2026-03-19T07:17:03.318Z"
      },
      "request_id": "",
      "request_path": "",
      "request_method": "",
      "request_status": null,
      "ip_address": "",
      "user_agent": "",
      "metadata": {},
      "previous_hash": "5e7ebe2fe10547e4b32b0eee0e48456de29e580da6f249f314d56eee23841d0c",
      "integrity_hash": "8468c1d0b31e44a6e438ab8a5f2a6a650492441c46dbaee3fc6563ae0a095f19",
      "created_at": "2026-03-19T07:17:03.320Z"
    }
  },
  {
    "model": "core.auditlog",
    "pk": 1004,
    "fields": {
      "event_id": "016bc1c8-1571-48ca-b38e-1e836e868112",
      "actor_user": null,
      "action": "created",
      "target_table": "learning.Registration",
      "target_id": "52",
      "before": {},
      "after": {
        "id": 52,
        "student": 29,
        "unit": 2,
        "academic_year": 2025,
        "trimester": 1,
        "status": "approved",
        "approved_by": null,
        "approved_at": "2026-03-19T07:17:03.322Z"
      },
      "request_id": "",
      "request_path": "",
      "request_method": "",
      "request_status": null,
      "ip_address": "",
      "user_agent": "",
      "metadata": {},
      "previous_hash": "8468c1d0b31e44a6e438ab8a5f2a6a650492441c46dbaee3fc6563ae0a095f19",
      "integrity_hash": "d318abbeb8c1bf92515230fe6a5132ea3967dec76f81cb7ade7362c8949b7e63",
      "created_at": "2026-03-19T07:17:03.323Z"
    }
  },
  {
    "model": "core.auditlog",
    "pk": 1005,
    "fields": {
      "event_id": "01a11f55-c787-443d-ad9e-33857e9e2537",
      "actor_user": null,
      "action": "created",
      "target_table": "learning.Registration",
      "target_id": "53",
      "before": {},
      "after": {
        "id": 53,
        "student": 29,
        "unit": 3,
        "academic_year": 2025,
        "trimester": 1,
        "status": "approved",
        "approved_by": null,
        "approved_at": "2026-03-19T07:17:03.327Z"
      },
      "request_id": "",
      "request_path": "",
      "request_method": "",
      "request_status": null,
      "ip_address": "",
      "user_agent": "",
      "metadata": {},
      "previous_hash": "d318abbeb8c1bf92515230fe6a5132ea3967dec76f81cb7ade7362c8949b7e63",
      "integrity_hash": "c4b0d2853db4e602e06dc188df093db3986e7bf86bd8818c6203a846845d8fd8",
      "created_at": "2026-03-19T07:17:03.329Z"
    }
  },
  {
    "model": "core.auditlog",
    "pk": 1006,
    "fields": {
      "event_id": "759d20bf-8edd-4d19-b604-34bd2dc58d14",
      "actor_user": null,
      "action": "created",
      "target_table": "communications.Thread",
      "target_id": "7",
      "before": {},
      "after": {
        "id": 7,
        "subject": "DTM101 lecturer channel",
        "student": 29,
        "teacher": 3,
        "parent": null
      },
      "request_id": "",
      "request_path": "",
      "request_method": "",
      "request_status": null,
      "ip_address": "",
      "user_agent": "",
      "metadata": {},
      "previous_hash": "c4b0d2853db4e602e06dc188df093db3986e7bf86bd8818c6203a846845d8fd8",
      "integrity_hash": "b0767f1dcb15e79257c37afec754aaa39ccd279cf8a40c1eaf962d35569a7423",
      "created_at": "2026-03-19T07:17:03.339Z"
    }
  },
  {
    "model": "core.auditlog",
    "pk": 1007,
    "fields": {
      "event_id": "00774aa6-b8c1-4b2a-92d9-33ad96f9104c",
      "actor_user": null,
      "action": "created",
      "target_table": "communications.Thread",
      "target_id": "8",
      "before": {},
      "after": {
        "id": 8,
        "subject": "DTM101 guardian channel",
        "student": 29,
        "teacher": 3,
        "parent": 30
      },
      "request_id": "",
      "request_path": "",
      "request_method": "",
      "request_status": null,
      "ip_address": "",
      "user_agent": "",
      "metadata": {},
      "previous_hash": "b0767f1dcb15e79257c37afec754aaa39ccd279cf8a40c1eaf962d35569a7423",
      "integrity_hash": "8cefc61d80fa3e5cf0ff2546118cbbc11d3bbe457e6fb043e52d52094fcee476",
      "created_at": "2026-03-19T07:17:03.343Z"
    }
  },
  {
    "model": "core.auditlog",
    "pk": 1008,
    "fields": {
      "event_id": "86e1eb8d-0618-4e79-9b4f-f25af5852b2a",
      "actor_user": null,
      "action": "created",
      "target_table": "communications.Thread",
      "target_id": "9",
      "before": {},
      "after": {
        "id": 9,
        "subject": "DTM103 lecturer channel",
        "student": 29,
        "teacher": 4,
        "parent": null
      },
      "request_id": "",
      "request_path": "",
      "request_method": "",
      "request_status": null,
      "ip_address": "",
      "user_agent": "",
      "metadata": {},
      "previous_hash": "8cefc61d80fa3e5cf0ff2546118cbbc11d3bbe457e6fb043e52d52094fcee476",
      "integrity_hash": "52e744ae4f8f788b2e5b13c19069236621ba88061c9050e584670f4613a3dc57",
      "created_at": "2026-03-19T07:17:03.353Z"
    }
  },
  {
    "model": "core.auditlog",
    "pk": 1009,
    "fields": {
      "event_id": "b8d9012f-f98b-4157-b6fd-a5490258fa37",
      "actor_user": null,
      "action": "created",
      "target_table": "communications.Thread",
      "target_id": "10",
      "before": {},
      "after": {
        "id": 10,
        "subject": "DTM103 guardian channel",
        "student": 29,
        "teacher": 4,
        "parent": 30
      },
      "request_id": "",
      "request_path": "",
      "request_method": "",
      "request_status": null,
      "ip_address": "",
      "user_agent": "",
      "metadata": {},
      "previous_hash": "52e744ae4f8f788b2e5b13c19069236621ba88061c9050e584670f4613a3dc57",
      "integrity_hash": "a88a0eba8d681ec76a318b08fa97e4859d1cdce52df3c977b4b3aa4f77a3e117",
      "created_at": "2026-03-19T07:17:03.356Z"
    }
  },
  {
    "model": "core.auditlog",
    "pk": 1010,
    "fields": {
      "event_id": "0dcdcedb-ed07-45eb-b8c5-3f0a83e47ba3",
      "actor_user": null,
      "action": "created",
      "target_table": "finance.FinanceStatus",
      "target_id": "20",
      "before": {},
      "after": {
        "id": 20,
        "student": 29,
        "academic_year": 2025,
        "trimester": 1,
        "total_due": "120000.00",
        "total_paid": "90000.00",
        "status": "partial",
        "clearance_status": "cleared_for_registration"
      },
      "request_id": "",
      "request_path": "",
      "request_method": "",
      "request_status": null,
      "ip_address": "",
      "user_agent": "",
      "metadata": {},
      "previous_hash": "a88a0eba8d681ec76a318b08fa97e4859d1cdce52df3c977b4b3aa4f77a3e117",
      "integrity_hash": "a510aa8b44c0bc1a30e53fbcb9c5b5491d13819168a38b43bead3b4195292827",
      "created_at": "2026-03-19T07:17:03.359Z"
    }
  },
  {
    "model": "core.auditlog",
    "pk": 1011,
    "fields": {
      "event_id": "5a11bb92-180f-4e85-adfd-3ac4ab14408a",
      "actor_user": null,
      "action": "updated",
      "target_table": "users.Student",
      "target_id": "29",
      "before": {},
      "after": {
        "user": 29,
        "programme": 1,
        "year": 1,
        "trimester": 1,
        "trimester_label": "Year 1, Trimester 1",
        "admission_date": "2026-03-12",
        "current_status": "active",
        "stars": 0
      },
      "request_id": "",
      "request_path": "",
      "request_method": "",
      "request_status": null,
      "ip_address": "",
      "user_agent": "",
      "metadata": {},
      "previous_hash": "a510aa8b44c0bc1a30e53fbcb9c5b5491d13819168a38b43bead3b4195292827",
      "integrity_hash": "0611bfbabc3ad0af128d1b5d7f40a9b1865753cace26c91fd61f103f77549991",
      "created_at": "2026-03-19T07:17:03.361Z"
    }
  },
  {
    "model": "core.auditlog",
    "pk": 1012,
    "fields": {
      "event_id": "cc5e53b4-51be-4203-b1a6-45ae4140e698",
      "actor_user": null,
      "action": "created",
      "target_table": "learning.Registration",
      "target_id": "54",
      "before": {},
      "after": {
        "id": 54,
        "student": 31,
        "unit": 1,
        "academic_year": 2025,
        "trimester": 1,
        "status": "approved",
        "approved_by": null,
        "approved_at": "2026-03-19T07:17:03.366Z"
      },
      "request_id": "",
      "request_path": "",
      "request_method": "",
      "request_status": null,
      "ip_address": "",
      "user_agent": "",
      "metadata": {},
      "previous_hash": "0611bfbabc3ad0af128d1b5d7f40a9b1865753cace26c91fd61f103f77549991",
      "integrity_hash": "da44555ba2381c9334ce3211109622c2a81a5c2887c0edfa163a46aee460e44b",
      "created_at": "2026-03-19T07:17:03.367Z"
    }
  },
  {
    "model": "core.auditlog",
    "pk": 1013,
    "fields": {
      "event_id": "0c617d61-b48b-431e-b07f-fb3d3bda49c2",
      "actor_user": null,
      "action": "created",
      "target_table": "learning.Registration",
      "target_id": "55",
      "before": {},
      "after": {
        "id": 55,
        "student": 31,
        "unit": 2,
        "academic_year": 2025,
        "trimester": 1,
        "status": "approved",
        "approved_by": null,
        "approved_at": "2026-03-19T07:17:03.370Z"
      },
      "request_id": "",
      "request_path": "",
      "request_method": "",
      "request_status": null,
      "ip_address": "",
      "user_agent": "",
      "metadata": {},
      "previous_hash": "da44555ba2381c9334ce3211109622c2a81a5c2887c0edfa163a46aee460e44b",
      "integrity_hash": "d55a05b696093ea07bb140d36ee91d8f6be5cd52364ba2991449a802d59e3f00",
      "created_at": "2026-03-19T07:17:03.371Z"
    }
  },
  {
    "model": "core.auditlog",
    "pk": 1014,
    "fields": {
      "event_id": "93168182-2580-4232-9519-6c5e109ba154",
      "actor_user": null,
      "action": "created",
      "target_table": "learning.Registration",
      "target_id": "56",
      "before": {},
      "after": {
        "id": 56,
        "student": 31,
        "unit": 3,
        "academic_year": 2025,
        "trimester": 1,
        "status": "approved",
        "approved_by": null,
        "approved_at": "2026-03-19T07:17:03.373Z"
      },
      "request_id": "",
      "request_path": "",
      "request_method": "",
      "request_status": null,
      "ip_address": "",
      "user_agent": "",
      "metadata": {},
      "previous_hash": "d55a05b696093ea07bb140d36ee91d8f6be5cd52364ba2991449a802d59e3f00",
      "integrity_hash": "728cbd6719265f3fd1665d62739a04fc50221665cc9da682735334084547922a",
      "created_at": "2026-03-19T07:17:03.374Z"
    }
  },
  {
    "model": "core.auditlog",
    "pk": 1015,
    "fields": {
      "event_id": "da2c8cad-c6d6-44f8-ac4c-4275fbb05285",
      "actor_user": null,
      "action": "created",
      "target_table": "communications.Thread",
      "target_id": "11",
      "before": {},
      "after": {
        "id": 11,
        "subject": "DTM101 lecturer channel",
        "student": 31,
        "teacher": 3,
        "parent": null
      },
      "request_id": "",
      "request_path": "",
      "request_method": "",
      "request_status": null,
      "ip_address": "",
      "user_agent": "",
      "metadata": {},
      "previous_hash": "728cbd6719265f3fd1665d62739a04fc50221665cc9da682735334084547922a",
      "integrity_hash": "2dd7ec05deb4ae9a933db28de6efc625ae7573b30524b986276eb304d1980d5e",
      "created_at": "2026-03-19T07:17:03.379Z"
    }
  },
  {
    "model": "core.auditlog",
    "pk": 1016,
    "fields": {
      "event_id": "84ac3970-21a7-460b-8812-616a4b789d36",
      "actor_user": null,
      "action": "created",
      "target_table": "communications.Thread",
      "target_id": "12",
      "before": {},
      "after": {
        "id": 12,
        "subject": "DTM101 guardian channel",
        "student": 31,
        "teacher": 3,
        "parent": 32
      },
      "request_id": "",
      "request_path": "",
      "request_method": "",
      "request_status": null,
      "ip_address": "",
      "user_agent": "",
      "metadata": {},
      "previous_hash": "2dd7ec05deb4ae9a933db28de6efc625ae7573b30524b986276eb304d1980d5e",
      "integrity_hash": "1389617a81d7d8083c8eab5b37f7bc7b8689efb6d4a212e02d0700523792e9c2",
      "created_at": "2026-03-19T07:17:03.381Z"
    }
  },
  {
    "model": "core.auditlog",
    "pk": 1017,
    "fields": {
      "event_id": "5ab5a539-d71c-4463-9d70-75b88e074267",
      "actor_user": null,
      "action": "created",
      "target_table": "communications.Thread",
      "target_id": "13",
      "before": {},
      "after": {
        "id": 13,
        "subject": "DTM103 lecturer channel",
        "student": 31,
        "teacher": 4,
        "parent": null
      },
      "request_id": "",
      "request_path": "",
      "request_method": "",
      "request_status": null,
      "ip_address": "",
      "user_agent": "",
      "metadata": {},
      "previous_hash": "1389617a81d7d8083c8eab5b37f7bc7b8689efb6d4a212e02d0700523792e9c2",
      "integrity_hash": "d498adc3c618fa02da6223de648b7ce3b64ebf9afc51cfa7e4675e2df67bdd67",
      "created_at": "2026-03-19T07:17:03.389Z"
    }
  },
  {
    "model": "core.auditlog",
    "pk": 1018,
    "fields": {
      "event_id": "895f56c6-ab2b-4338-9fe7-829a247fa1bb",
      "actor_user": null,
      "action": "created",
      "target_table": "communications.Thread",
      "target_id": "14",
      "before": {},
      "after": {
        "id": 14,
        "subject": "DTM103 guardian channel",
        "student": 31,
        "teacher": 4,
        "parent": 32
      },
      "request_id": "",
      "request_path": "",
      "request_method": "",
      "request_status": null,
      "ip_address": "",
      "user_agent": "",
      "metadata": {},
      "previous_hash": "d498adc3c618fa02da6223de648b7ce3b64ebf9afc51cfa7e4675e2df67bdd67",
      "integrity_hash": "6957ed3eb922d0416b9de12c3e32f6b6e271bd3862ffbc39345aa0fdfd67426c",
      "created_at": "2026-03-19T07:17:03.392Z"
    }
  },
  {
    "model": "core.auditlog",
    "pk": 1019,
    "fields": {
      "event_id": "1de1e48d-1ca0-43a0-a8ec-e75d3ffaeb83",
      "actor_user": null,
      "action": "created",
      "target_table": "finance.FinanceStatus",
      "target_id": "21",
      "before": {},
      "after": {
        "id": 21,
        "student": 31,
        "academic_year": 2025,
        "trimester": 1,
        "total_due": "120000.00",
        "total_paid": "90000.00",
        "status": "partial",
        "clearance_status": "cleared_for_registration"
      },
      "request_id": "",
      "request_path": "",
      "request_method": "",
      "request_status": null,
      "ip_address": "",
      "user_agent": "",
      "metadata": {},
      "previous_hash": "6957ed3eb922d0416b9de12c3e32f6b6e271bd3862ffbc39345aa0fdfd67426c",
      "integrity_hash": "251333aa4c4f0be192e4864846c2b2942e4d5bf4c5ceda29acee8db9126ce297",
      "created_at": "2026-03-19T07:17:03.394Z"
    }
  },
  {
    "model": "core.auditlog",
    "pk": 1020,
    "fields": {
      "event_id": "3af3fe3f-9e66-42f6-af91-a0a41761d5da",
      "actor_user": null,
      "action": "updated",
      "target_table": "users.Student",
      "target_id": "31",
      "before": {},
      "after": {
        "user": 31,
        "programme": 1,
        "year": 1,
        "trimester": 1,
        "trimester_label": "Year 1, Trimester 1",
        "admission_date": "2026-03-12",
        "current_status": "active",
        "stars": 0
      },
      "request_id": "",
      "request_path": "",
      "request_method": "",
      "request_status": null,
      "ip_address": "",
      "user_agent": "",
      "metadata": {},
      "previous_hash": "251333aa4c4f0be192e4864846c2b2942e4d5bf4c5ceda29acee8db9126ce297",
      "integrity_hash": "3ed134f7c5d5f92aafdbf7b9e82617c3122a2fda0751d905c97be75d8f19fa00",
      "created_at": "2026-03-19T07:17:03.395Z"
    }
  },
  {
    "model": "core.auditlog",
    "pk": 1021,
    "fields": {
      "event_id": "30a5886b-c273-4a35-ba34-ab7a9c716fc4",
      "actor_user": null,
      "action": "created",
      "target_table": "learning.Registration",
      "target_id": "57",
      "before": {},
      "after": {
        "id": 57,
        "student": 33,
        "unit": 1,
        "academic_year": 2025,
        "trimester": 1,
        "status": "approved",
        "approved_by": null,
        "approved_at": "2026-03-19T07:17:03.400Z"
      },
      "request_id": "",
      "request_path": "",
      "request_method": "",
      "request_status": null,
      "ip_address": "",
      "user_agent": "",
      "metadata": {},
      "previous_hash": "3ed134f7c5d5f92aafdbf7b9e82617c3122a2fda0751d905c97be75d8f19fa00",
      "integrity_hash": "177a0b61643136ac7b2b5339774a7b61b0c77b86c27b4068e8ad55ea22bcc457",
      "created_at": "2026-03-19T07:17:03.402Z"
    }
  },
  {
    "model": "core.auditlog",
    "pk": 1022,
    "fields": {
      "event_id": "cbc724f1-a0f9-4ff9-8bcb-532dbd1c2005",
      "actor_user": null,
      "action": "created",
      "target_table": "learning.Registration",
      "target_id": "58",
      "before": {},
      "after": {
        "id": 58,
        "student": 33,
        "unit": 2,
        "academic_year": 2025,
        "trimester": 1,
        "status": "approved",
        "approved_by": null,
        "approved_at": "2026-03-19T07:17:03.404Z"
      },
      "request_id": "",
      "request_path": "",
      "request_method": "",
      "request_status": null,
      "ip_address": "",
      "user_agent": "",
      "metadata": {},
      "previous_hash": "177a0b61643136ac7b2b5339774a7b61b0c77b86c27b4068e8ad55ea22bcc457",
      "integrity_hash": "e927c928a404ff2d63c6abbceb6488e0ffd14093658069193175389a7adbb8fa",
      "created_at": "2026-03-19T07:17:03.405Z"
    }
  },
  {
    "model": "core.auditlog",
    "pk": 1023,
    "fields": {
      "event_id": "f86933bc-52e6-458c-9682-114829d589f2",
      "actor_user": null,
      "action": "created",
      "target_table": "learning.Registration",
      "target_id": "59",
      "before": {},
      "after": {
        "id": 59,
        "student": 33,
        "unit": 3,
        "academic_year": 2025,
        "trimester": 1,
        "status": "approved",
        "approved_by": null,
        "approved_at": "2026-03-19T07:17:03.407Z"
      },
      "request_id": "",
      "request_path": "",
      "request_method": "",
      "request_status": null,
      "ip_address": "",
      "user_agent": "",
      "metadata": {},
      "previous_hash": "e927c928a404ff2d63c6abbceb6488e0ffd14093658069193175389a7adbb8fa",
      "integrity_hash": "f6f6098ee23f05c3ddb69337ee7ce8b998fa1f563463e7c6f253cf69506c3ccc",
      "created_at": "2026-03-19T07:17:03.408Z"
    }
  },
  {
    "model": "core.auditlog",
    "pk": 1024,
    "fields": {
      "event_id": "06d7441f-5fb0-41d0-8b3d-ae495cdb2617",
      "actor_user": null,
      "action": "created",
      "target_table": "communications.Thread",
      "target_id": "15",
      "before": {},
      "after": {
        "id": 15,
        "subject": "DTM101 lecturer channel",
        "student": 33,
        "teacher": 3,
        "parent": null
      },
      "request_id": "",
      "request_path": "",
      "request_method": "",
      "request_status": null,
      "ip_address": "",
      "user_agent": "",
      "metadata": {},
      "previous_hash": "f6f6098ee23f05c3ddb69337ee7ce8b998fa1f563463e7c6f253cf69506c3ccc",
      "integrity_hash": "436f3300788a6c01f4890eb328893747eaf5e7357eda4cd8ebcb4139ddfe1251",
      "created_at": "2026-03-19T07:17:03.414Z"
    }
  },
  {
    "model": "core.auditlog",
    "pk": 1025,
    "fields": {
      "event_id": "14bbb801-27fa-4794-9b21-5d2f78ec840b",
      "actor_user": null,
      "action": "created",
      "target_table": "communications.Thread",
      "target_id": "16",
      "before": {},
      "after": {
        "id": 16,
        "subject": "DTM101 guardian channel",
        "student": 33,
        "teacher": 3,
        "parent": 34
      },
      "request_id": "",
      "request_path": "",
      "request_method": "",
      "request_status": null,
      "ip_address": "",
      "user_agent": "",
      "metadata": {},
      "previous_hash": "436f3300788a6c01f4890eb328893747eaf5e7357eda4cd8ebcb4139ddfe1251",
      "integrity_hash": "686afb9b69194a5427052231a8ffab536829325dad275f5fd814764329c62f81",
      "created_at": "2026-03-19T07:17:03.417Z"
    }
  },
  {
    "model": "core.auditlog",
    "pk": 1026,
    "fields": {
      "event_id": "54162677-8dd6-4454-9423-6487bcb34cfe",
      "actor_user": null,
      "action": "created",
      "target_table": "communications.Thread",
      "target_id": "17",
      "before": {},
      "after": {
        "id": 17,
        "subject": "DTM103 lecturer channel",
        "student": 33,
        "teacher": 4,
        "parent": null
      },
      "request_id": "",
      "request_path": "",
      "request_method": "",
      "request_status": null,
      "ip_address": "",
      "user_agent": "",
      "metadata": {},
      "previous_hash": "686afb9b69194a5427052231a8ffab536829325dad275f5fd814764329c62f81",
      "integrity_hash": "2a9424ed1eb2e39e83b56a1a41984d1b0c360f4aa7a20c7089197f45e5716958",
      "created_at": "2026-03-19T07:17:03.426Z"
    }
  },
  {
    "model": "core.auditlog",
    "pk": 1027,
    "fields": {
      "event_id": "79bcedd8-4226-49da-9329-5a7975292dd3",
      "actor_user": null,
      "action": "created",
      "target_table": "communications.Thread",
      "target_id": "18",
      "before": {},
      "after": {
        "id": 18,
        "subject": "DTM103 guardian channel",
        "student": 33,
        "teacher": 4,
        "parent": 34
      },
      "request_id": "",
      "request_path": "",
      "request_method": "",
      "request_status": null,
      "ip_address": "",
      "user_agent": "",
      "metadata": {},
      "previous_hash": "2a9424ed1eb2e39e83b56a1a41984d1b0c360f4aa7a20c7089197f45e5716958",
      "integrity_hash": "e26c9a6364a3143d2ff9f0d661dcf591c12988497a033890455223ee7a82841c",
      "created_at": "2026-03-19T07:17:03.429Z"
    }
  },
  {
    "model": "core.auditlog",
    "pk": 1028,
    "fields": {
      "event_id": "be33eb3e-2a17-4246-9253-0a0fb8237eb2",
      "actor_user": null,
      "action": "created",
      "target_table": "finance.FinanceStatus",
      "target_id": "22",
      "before": {},
      "after": {
        "id": 22,
        "student": 33,
        "academic_year": 2025,
        "trimester": 1,
        "total_due": "120000.00",
        "total_paid": "90000.00",
        "status": "partial",
        "clearance_status": "cleared_for_registration"
      },
      "request_id": "",
      "request_path": "",
      "request_method": "",
      "request_status": null,
      "ip_address": "",
      "user_agent": "",
      "metadata": {},
      "previous_hash": "e26c9a6364a3143d2ff9f0d661dcf591c12988497a033890455223ee7a82841c",
      "integrity_hash": "6f1b85494ccbe84487cd054dedcd25d3d8623069305f3c829e54ff077aedc71c",
      "created_at": "2026-03-19T07:17:03.433Z"
    }
  },
  {
    "model": "core.auditlog",
    "pk": 1029,
    "fields": {
      "event_id": "542b4e06-5b2e-47d3-8f29-e971e5471efe",
      "actor_user": null,
      "action": "updated",
      "target_table": "users.Student",
      "target_id": "33",
      "before": {},
      "after": {
        "user": 33,
        "programme": 1,
        "year": 2,
        "trimester": 1,
        "trimester_label": "Year 2, Trimester 1",
        "admission_date": "2026-03-12",
        "current_status": "active",
        "stars": 0
      },
      "request_id": "",
      "request_path": "",
      "request_method": "",
      "request_status": null,
      "ip_address": "",
      "user_agent": "",
      "metadata": {},
      "previous_hash": "6f1b85494ccbe84487cd054dedcd25d3d8623069305f3c829e54ff077aedc71c",
      "integrity_hash": "faafa79ad4733666c6f9f0edbf9983ebc478366fe5262a1fb58385c3dbc29ad1",
      "created_at": "2026-03-19T07:17:03.435Z"
    }
  },
  {
    "model": "core.auditlog",
    "pk": 1030,
    "fields": {
      "event_id": "5726a5a9-b80f-41f1-8b07-d03593512594",
      "actor_user": null,
      "action": "created",
      "target_table": "learning.Registration",
      "target_id": "60",
      "before": {},
      "after": {
        "id": 60,
        "student": 35,
        "unit": 1,
        "academic_year": 2025,
        "trimester": 1,
        "status": "approved",
        "approved_by": null,
        "approved_at": "2026-03-19T07:17:03.440Z"
      },
      "request_id": "",
      "request_path": "",
      "request_method": "",
      "request_status": null,
      "ip_address": "",
      "user_agent": "",
      "metadata": {},
      "previous_hash": "faafa79ad4733666c6f9f0edbf9983ebc478366fe5262a1fb58385c3dbc29ad1",
      "integrity_hash": "7861b556e34cd96cf4f4009b8a3c78d8532126d8211f890be13bd7683a1d9206",
      "created_at": "2026-03-19T07:17:03.441Z"
    }
  },
  {
    "model": "core.auditlog",
    "pk": 1031,
    "fields": {
      "event_id": "18eb62d3-63d9-4411-9802-402c01b6c8ec",
      "actor_user": null,
      "action": "created",
      "target_table": "learning.Registration",
      "target_id": "61",
      "before": {},
      "after": {
        "id": 61,
        "student": 35,
        "unit": 2,
        "academic_year": 2025,
        "trimester": 1,
        "status": "approved",
        "approved_by": null,
        "approved_at": "2026-03-19T07:17:03.443Z"
      },
      "request_id": "",
      "request_path": "",
      "request_method": "",
      "request_status": null,
      "ip_address": "",
      "user_agent": "",
      "metadata": {},
      "previous_hash": "7861b556e34cd96cf4f4009b8a3c78d8532126d8211f890be13bd7683a1d9206",
      "integrity_hash": "a91da7dcc3c5b210aea3b762dabd9cc483ce9e025a537c2a2835f75490eba530",
      "created_at": "2026-03-19T07:17:03.445Z"
    }
  },
  {
    "model": "core.auditlog",
    "pk": 1032,
    "fields": {
      "event_id": "88965ab5-5d4a-41a6-8f13-d491d26ed335",
      "actor_user": null,
      "action": "created",
      "target_table": "learning.Registration",
      "target_id": "62",
      "before": {},
      "after": {
        "id": 62,
        "student": 35,
        "unit": 3,
        "academic_year": 2025,
        "trimester": 1,
        "status": "approved",
        "approved_by": null,
        "approved_at": "2026-03-19T07:17:03.446Z"
      },
      "request_id": "",
      "request_path": "",
      "request_method": "",
      "request_status": null,
      "ip_address": "",
      "user_agent": "",
      "metadata": {},
      "previous_hash": "a91da7dcc3c5b210aea3b762dabd9cc483ce9e025a537c2a2835f75490eba530",
      "integrity_hash": "b21efd9de4ebfbad73fd6a4c2d44a548cd411bc96c6093afe8bfe28fc2d4b951",
      "created_at": "2026-03-19T07:17:03.448Z"
    }
  },
  {
    "model": "core.auditlog",
    "pk": 1033,
    "fields": {
      "event_id": "ea29cc67-5cdd-478f-a7c6-4106ca005055",
      "actor_user": null,
      "action": "created",
      "target_table": "communications.Thread",
      "target_id": "19",
      "before": {},
      "after": {
        "id": 19,
        "subject": "DTM101 lecturer channel",
        "student": 35,
        "teacher": 3,
        "parent": null
      },
      "request_id": "",
      "request_path": "",
      "request_method": "",
      "request_status": null,
      "ip_address": "",
      "user_agent": "",
      "metadata": {},
      "previous_hash": "b21efd9de4ebfbad73fd6a4c2d44a548cd411bc96c6093afe8bfe28fc2d4b951",
      "integrity_hash": "cf2476c0901ceea46c556585dd779cc8da1a6f7df92d4a2a304fa4a1dfb29902",
      "created_at": "2026-03-19T07:17:03.453Z"
    }
  },
  {
    "model": "core.auditlog",
    "pk": 1034,
    "fields": {
      "event_id": "387569cb-e8aa-4763-99e3-90e9995248d0",
      "actor_user": null,
      "action": "created",
      "target_table": "communications.Thread",
      "target_id": "20",
      "before": {},
      "after": {
        "id": 20,
        "subject": "DTM101 guardian channel",
        "student": 35,
        "teacher": 3,
        "parent": 36
      },
      "request_id": "",
      "request_path": "",
      "request_method": "",
      "request_status": null,
      "ip_address": "",
      "user_agent": "",
      "metadata": {},
      "previous_hash": "cf2476c0901ceea46c556585dd779cc8da1a6f7df92d4a2a304fa4a1dfb29902",
      "integrity_hash": "cb0da1e58a6301e0e6a708b11ae94d6d5d9c84113e25ed9ad5541c7602caf157",
      "created_at": "2026-03-19T07:17:03.455Z"
    }
  },
  {
    "model": "core.auditlog",
    "pk": 1035,
    "fields": {
      "event_id": "924df1f0-afbd-49ed-afb0-89d6ee16dfb2",
      "actor_user": null,
      "action": "created",
      "target_table": "communications.Thread",
      "target_id": "21",
      "before": {},
      "after": {
        "id": 21,
        "subject": "DTM103 lecturer channel",
        "student": 35,
        "teacher": 4,
        "parent": null
      },
      "request_id": "",
      "request_path": "",
      "request_method": "",
      "request_status": null,
      "ip_address": "",
      "user_agent": "",
      "metadata": {},
      "previous_hash": "cb0da1e58a6301e0e6a708b11ae94d6d5d9c84113e25ed9ad5541c7602caf157",
      "integrity_hash": "c10231938089323ad24f52697b9ae635a7ae5b552fe227387628ba4589c29d97",
      "created_at": "2026-03-19T07:17:03.464Z"
    }
  },
  {
    "model": "core.auditlog",
    "pk": 1036,
    "fields": {
      "event_id": "fad0ef54-5341-496f-ae33-80aeaa8d3d9d",
      "actor_user": null,
      "action": "created",
      "target_table": "communications.Thread",
      "target_id": "22",
      "before": {},
      "after": {
        "id": 22,
        "subject": "DTM103 guardian channel",
        "student": 35,
        "teacher": 4,
        "parent": 36
      },
      "request_id": "",
      "request_path": "",
      "request_method": "",
      "request_status": null,
      "ip_address": "",
      "user_agent": "",
      "metadata": {},
      "previous_hash": "c10231938089323ad24f52697b9ae635a7ae5b552fe227387628ba4589c29d97",
      "integrity_hash": "e34e739ca8ddf5c605170eb662d04fb38e98dd9df3400fbffadfc321421b0775",
      "created_at": "2026-03-19T07:17:03.468Z"
    }
  },
  {
    "model": "core.auditlog",
    "pk": 1037,
    "fields": {
      "event_id": "def63464-afe3-46b2-945d-893881a84e7c",
      "actor_user": null,
      "action": "created",
      "target_table": "finance.FinanceStatus",
      "target_id": "23",
      "before": {},
      "after": {
        "id": 23,
        "student": 35,
        "academic_year": 2025,
        "trimester": 1,
        "total_due": "120000.00",
        "total_paid": "90000.00",
        "status": "partial",
        "clearance_status": "cleared_for_registration"
      },
      "request_id": "",
      "request_path": "",
      "request_method": "",
      "request_status": null,
      "ip_address": "",
      "user_agent": "",
      "metadata": {},
      "previous_hash": "e34e739ca8ddf5c605170eb662d04fb38e98dd9df3400fbffadfc321421b0775",
      "integrity_hash": "fb5a12bf7a8656f43fc0ae29d5475f2399940a4b1cec17288fdb42f0a1d39e6e",
      "created_at": "2026-03-19T07:17:03.471Z"
    }
  },
  {
    "model": "core.auditlog",
    "pk": 1038,
    "fields": {
      "event_id": "b0c348f7-02b1-48d9-863f-435264f0270c",
      "actor_user": null,
      "action": "updated",
      "target_table": "users.Student",
      "target_id": "35",
      "before": {},
      "after": {
        "user": 35,
        "programme": 1,
        "year": 2,
        "trimester": 1,
        "trimester_label": "Year 2, Trimester 1",
        "admission_date": "2026-03-12",
        "current_status": "active",
        "stars": 0
      },
      "request_id": "",
      "request_path": "",
      "request_method": "",
      "request_status": null,
      "ip_address": "",
      "user_agent": "",
      "metadata": {},
      "previous_hash": "fb5a12bf7a8656f43fc0ae29d5475f2399940a4b1cec17288fdb42f0a1d39e6e",
      "integrity_hash": "e61c33e1a3a2057d9ba9fc4e091426ba1df2ff31d916aee5b895a75b7b76d266",
      "created_at": "2026-03-19T07:17:03.474Z"
    }
  },
  {
    "model": "core.auditlog",
    "pk": 1039,
    "fields": {
      "event_id": "f1c15ccf-c873-485f-944f-1ce8e62a45b4",
      "actor_user": null,
      "action": "created",
      "target_table": "learning.Registration",
      "target_id": "63",
      "before": {},
      "after": {
        "id": 63,
        "student": 37,
        "unit": 1,
        "academic_year": 2025,
        "trimester": 1,
        "status": "approved",
        "approved_by": null,
        "approved_at": "2026-03-19T07:17:03.478Z"
      },
      "request_id": "",
      "request_path": "",
      "request_method": "",
      "request_status": null,
      "ip_address": "",
      "user_agent": "",
      "metadata": {},
      "previous_hash": "e61c33e1a3a2057d9ba9fc4e091426ba1df2ff31d916aee5b895a75b7b76d266",
      "integrity_hash": "bf2960f82a5ed60bb95d642a712a68f77a4f3b05f6dd29e215f0595edf240a6c",
      "created_at": "2026-03-19T07:17:03.479Z"
    }
  },
  {
    "model": "core.auditlog",
    "pk": 1040,
    "fields": {
      "event_id": "293b8ba7-facc-4cdf-82c7-bd90b3663333",
      "actor_user": null,
      "action": "created",
      "target_table": "learning.Registration",
      "target_id": "64",
      "before": {},
      "after": {
        "id": 64,
        "student": 37,
        "unit": 2,
        "academic_year": 2025,
        "trimester": 1,
        "status": "approved",
        "approved_by": null,
        "approved_at": "2026-03-19T07:17:03.481Z"
      },
      "request_id": "",
      "request_path": "",
      "request_method": "",
      "request_status": null,
      "ip_address": "",
      "user_agent": "",
      "metadata": {},
      "previous_hash": "bf2960f82a5ed60bb95d642a712a68f77a4f3b05f6dd29e215f0595edf240a6c",
      "integrity_hash": "dda54da6f2076870cd54ac43514b5a6abc0d86972cae0f757b27654df3f2295c",
      "created_at": "2026-03-19T07:17:03.483Z"
    }
  },
  {
    "model": "core.auditlog",
    "pk": 1041,
    "fields": {
      "event_id": "e9732551-e338-4545-b08d-0411dd059ea0",
      "actor_user": null,
      "action": "created",
      "target_table": "learning.Registration",
      "target_id": "65",
      "before": {},
      "after": {
        "id": 65,
        "student": 37,
        "unit": 3,
        "academic_year": 2025,
        "trimester": 1,
        "status": "approved",
        "approved_by": null,
        "approved_at": "2026-03-19T07:17:03.485Z"
      },
      "request_id": "",
      "request_path": "",
      "request_method": "",
      "request_status": null,
      "ip_address": "",
      "user_agent": "",
      "metadata": {},
      "previous_hash": "dda54da6f2076870cd54ac43514b5a6abc0d86972cae0f757b27654df3f2295c",
      "integrity_hash": "20759af8d56a17dbb0b9fd0a2d98429a197235ae04aa563b4db2ad396666e5e0",
      "created_at": "2026-03-19T07:17:03.486Z"
    }
  },
  {
    "model": "core.auditlog",
    "pk": 1042,
    "fields": {
      "event_id": "c3051330-7ffc-43ed-a486-fb410a2c08f4",
      "actor_user": null,
      "action": "created",
      "target_table": "communications.Thread",
      "target_id": "23",
      "before": {},
      "after": {
        "id": 23,
        "subject": "DTM101 lecturer channel",
        "student": 37,
        "teacher": 3,
        "parent": null
      },
      "request_id": "",
      "request_path": "",
      "request_method": "",
      "request_status": null,
      "ip_address": "",
      "user_agent": "",
      "metadata": {},
      "previous_hash": "20759af8d56a17dbb0b9fd0a2d98429a197235ae04aa563b4db2ad396666e5e0",
      "integrity_hash": "96c792c8bf9906815cc22208007c1c52688018f06f4b4c5de0136ef2916d1753",
      "created_at": "2026-03-19T07:17:03.492Z"
    }
  },
  {
    "model": "core.auditlog",
    "pk": 1043,
    "fields": {
      "event_id": "bdf43fbb-d2e8-4629-aaf4-c97eef3aa802",
      "actor_user": null,
      "action": "created",
      "target_table": "communications.Thread",
      "target_id": "24",
      "before": {},
      "after": {
        "id": 24,
        "subject": "DTM101 guardian channel",
        "student": 37,
        "teacher": 3,
        "parent": 38
      },
      "request_id": "",
      "request_path": "",
      "request_method": "",
      "request_status": null,
      "ip_address": "",
      "user_agent": "",
      "metadata": {},
      "previous_hash": "96c792c8bf9906815cc22208007c1c52688018f06f4b4c5de0136ef2916d1753",
      "integrity_hash": "f39d8ca1df28deb1e425ed7befe302609cbb4767189f4b4a2c8e73b553bf97db",
      "created_at": "2026-03-19T07:17:03.495Z"
    }
  },
  {
    "model": "core.auditlog",
    "pk": 1044,
    "fields": {
      "event_id": "aa8c8689-c383-462c-ae25-e8cfb8993c45",
      "actor_user": null,
      "action": "created",
      "target_table": "communications.Thread",
      "target_id": "25",
      "before": {},
      "after": {
        "id": 25,
        "subject": "DTM103 lecturer channel",
        "student": 37,
        "teacher": 4,
        "parent": null
      },
      "request_id": "",
      "request_path": "",
      "request_method": "",
      "request_status": null,
      "ip_address": "",
      "user_agent": "",
      "metadata": {},
      "previous_hash": "f39d8ca1df28deb1e425ed7befe302609cbb4767189f4b4a2c8e73b553bf97db",
      "integrity_hash": "d19639cc1be65d023a288256d2f923b166170745cf725a53b15b85dafd139660",
      "created_at": "2026-03-19T07:17:03.504Z"
    }
  },
  {
    "model": "core.auditlog",
    "pk": 1045,
    "fields": {
      "event_id": "d0745dd5-40d7-4dc3-8eef-865049329025",
      "actor_user": null,
      "action": "created",
      "target_table": "communications.Thread",
      "target_id": "26",
      "before": {},
      "after": {
        "id": 26,
        "subject": "DTM103 guardian channel",
        "student": 37,
        "teacher": 4,
        "parent": 38
      },
      "request_id": "",
      "request_path": "",
      "request_method": "",
      "request_status": null,
      "ip_address": "",
      "user_agent": "",
      "metadata": {},
      "previous_hash": "d19639cc1be65d023a288256d2f923b166170745cf725a53b15b85dafd139660",
      "integrity_hash": "aecfe263b28c03aa48cc844fdee91a16de9e5e87e247a69ad73d172f24b26fea",
      "created_at": "2026-03-19T07:17:03.507Z"
    }
  },
  {
    "model": "core.auditlog",
    "pk": 1046,
    "fields": {
      "event_id": "a8557b56-438a-472a-9156-977ca84062fb",
      "actor_user": null,
      "action": "created",
      "target_table": "finance.FinanceStatus",
      "target_id": "24",
      "before": {},
      "after": {
        "id": 24,
        "student": 37,
        "academic_year": 2025,
        "trimester": 1,
        "total_due": "120000.00",
        "total_paid": "90000.00",
        "status": "partial",
        "clearance_status": "cleared_for_registration"
      },
      "request_id": "",
      "request_path": "",
      "request_method": "",
      "request_status": null,
      "ip_address": "",
      "user_agent": "",
      "metadata": {},
      "previous_hash": "aecfe263b28c03aa48cc844fdee91a16de9e5e87e247a69ad73d172f24b26fea",
      "integrity_hash": "180e9512d85bcdf275e1075f5e17530e652d31e5a5d3d4ef8d060dcab469c556",
      "created_at": "2026-03-19T07:17:03.509Z"
    }
  },
  {
    "model": "core.auditlog",
    "pk": 1047,
    "fields": {
      "event_id": "d117d351-d798-4586-8c17-98368ff2ebcc",
      "actor_user": null,
      "action": "updated",
      "target_table": "users.Student",
      "target_id": "37",
      "before": {},
      "after": {
        "user": 37,
        "programme": 1,
        "year": 2,
        "trimester": 1,
        "trimester_label": "Year 2, Trimester 1",
        "admission_date": "2026-03-12",
        "current_status": "active",
        "stars": 0
      },
      "request_id": "",
      "request_path": "",
      "request_method": "",
      "request_status": null,
      "ip_address": "",
      "user_agent": "",
      "metadata": {},
      "previous_hash": "180e9512d85bcdf275e1075f5e17530e652d31e5a5d3d4ef8d060dcab469c556",
      "integrity_hash": "3706ade37bebe7eee2307dd082c2eb37204262a1fb3573d913f904734765a000",
      "created_at": "2026-03-19T07:17:03.512Z"
    }
  },
  {
    "model": "core.auditlog",
    "pk": 1048,
    "fields": {
      "event_id": "4040daed-d84e-4569-833a-f15b2d6aed00",
      "actor_user": null,
      "action": "created",
      "target_table": "learning.Registration",
      "target_id": "66",
      "before": {},
      "after": {
        "id": 66,
        "student": 13,
        "unit": 22,
        "academic_year": 2,
        "trimester": 1,
        "status": "approved",
        "approved_by": null,
        "approved_at": "2026-03-19T07:17:03.517Z"
      },
      "request_id": "",
      "request_path": "",
      "request_method": "",
      "request_status": null,
      "ip_address": "",
      "user_agent": "",
      "metadata": {},
      "previous_hash": "3706ade37bebe7eee2307dd082c2eb37204262a1fb3573d913f904734765a000",
      "integrity_hash": "3fe19da98f3b6a6ce83915541ca18aa22b55ab894980b0179ca2068a2f30fa66",
      "created_at": "2026-03-19T07:17:03.518Z"
    }
  },
  {
    "model": "core.auditlog",
    "pk": 1049,
    "fields": {
      "event_id": "6515bfd7-c668-4234-91c7-ea9c22a4a19d",
      "actor_user": null,
      "action": "created",
      "target_table": "learning.Registration",
      "target_id": "67",
      "before": {},
      "after": {
        "id": 67,
        "student": 13,
        "unit": 23,
        "academic_year": 2,
        "trimester": 1,
        "status": "approved",
        "approved_by": null,
        "approved_at": "2026-03-19T07:17:03.520Z"
      },
      "request_id": "",
      "request_path": "",
      "request_method": "",
      "request_status": null,
      "ip_address": "",
      "user_agent": "",
      "metadata": {},
      "previous_hash": "3fe19da98f3b6a6ce83915541ca18aa22b55ab894980b0179ca2068a2f30fa66",
      "integrity_hash": "999c45a074247bbcdf8417c38c9ce49df4e813d07f54dee54a8b64e7bd8c4b0e",
      "created_at": "2026-03-19T07:17:03.522Z"
    }
  },
  {
    "model": "core.auditlog",
    "pk": 1050,
    "fields": {
      "event_id": "caf599aa-40b7-438e-b5c3-93facd45ea45",
      "actor_user": null,
      "action": "created",
      "target_table": "learning.Registration",
      "target_id": "68",
      "before": {},
      "after": {
        "id": 68,
        "student": 13,
        "unit": 24,
        "academic_year": 2,
        "trimester": 1,
        "status": "approved",
        "approved_by": null,
        "approved_at": "2026-03-19T07:17:03.524Z"
      },
      "request_id": "",
      "request_path": "",
      "request_method": "",
      "request_status": null,
      "ip_address": "",
      "user_agent": "",
      "metadata": {},
      "previous_hash": "999c45a074247bbcdf8417c38c9ce49df4e813d07f54dee54a8b64e7bd8c4b0e",
      "integrity_hash": "86f84f2ab1bc7e65df1cd66ee9d4499897f2ffac9ff09dc58b6a7788d8ed497e",
      "created_at": "2026-03-19T07:17:03.526Z"
    }
  },
  {
    "model": "core.auditlog",
    "pk": 1051,
    "fields": {
      "event_id": "23fb1e42-6da2-416d-aeba-de8e5ef07348",
      "actor_user": null,
      "action": "created",
      "target_table": "learning.LecturerAssignment",
      "target_id": "37",
      "before": {},
      "after": {
        "id": 37,
        "lecturer": 3,
        "unit": 22,
        "academic_year": 2,
        "trimester": 1
      },
      "request_id": "",
      "request_path": "",
      "request_method": "",
      "request_status": null,
      "ip_address": "",
      "user_agent": "",
      "metadata": {},
      "previous_hash": "86f84f2ab1bc7e65df1cd66ee9d4499897f2ffac9ff09dc58b6a7788d8ed497e",
      "integrity_hash": "b7c423ad4daf6828492941730a5080895a4ce1aa3eb94700e19389fc668a39bd",
      "created_at": "2026-03-19T07:17:03.535Z"
    }
  },
  {
    "model": "core.auditlog",
    "pk": 1052,
    "fields": {
      "event_id": "09167b99-0fa0-485b-94ea-7c6fade7c99c",
      "actor_user": null,
      "action": "created",
      "target_table": "communications.Thread",
      "target_id": "27",
      "before": {},
      "after": {
        "id": 27,
        "subject": "TT-211 lecturer channel",
        "student": 13,
        "teacher": 3,
        "parent": null
      },
      "request_id": "",
      "request_path": "",
      "request_method": "",
      "request_status": null,
      "ip_address": "",
      "user_agent": "",
      "metadata": {},
      "previous_hash": "b7c423ad4daf6828492941730a5080895a4ce1aa3eb94700e19389fc668a39bd",
      "integrity_hash": "201c75b63255c47cd7b20e2cad372be2aa73d08fbceb53d6e9259ada8c87194f",
      "created_at": "2026-03-19T07:17:03.539Z"
    }
  },
  {
    "model": "core.auditlog",
    "pk": 1053,
    "fields": {
      "event_id": "895d9fd1-4afd-4e94-ad95-e13e63a98fb8",
      "actor_user": null,
      "action": "created",
      "target_table": "communications.Thread",
      "target_id": "28",
      "before": {},
      "after": {
        "id": 28,
        "subject": "TT-211 guardian channel",
        "student": 13,
        "teacher": 3,
        "parent": 14
      },
      "request_id": "",
      "request_path": "",
      "request_method": "",
      "request_status": null,
      "ip_address": "",
      "user_agent": "",
      "metadata": {},
      "previous_hash": "201c75b63255c47cd7b20e2cad372be2aa73d08fbceb53d6e9259ada8c87194f",
      "integrity_hash": "78509e86ab1255b9c8d6d108bdce8b696bc30b147600a84f70154434248b2d21",
      "created_at": "2026-03-19T07:17:03.542Z"
    }
  },
  {
    "model": "core.auditlog",
    "pk": 1054,
    "fields": {
      "event_id": "df5ef769-4e1e-48c8-8383-9b140e924255",
      "actor_user": null,
      "action": "created",
      "target_table": "learning.LecturerAssignment",
      "target_id": "38",
      "before": {},
      "after": {
        "id": 38,
        "lecturer": 3,
        "unit": 23,
        "academic_year": 2,
        "trimester": 1
      },
      "request_id": "",
      "request_path": "",
      "request_method": "",
      "request_status": null,
      "ip_address": "",
      "user_agent": "",
      "metadata": {},
      "previous_hash": "78509e86ab1255b9c8d6d108bdce8b696bc30b147600a84f70154434248b2d21",
      "integrity_hash": "b91974cb3f1a7542a75300d1e586d1bcfca8c883de3a3af8890dfe73a322b195",
      "created_at": "2026-03-19T07:17:03.549Z"
    }
  },
  {
    "model": "core.auditlog",
    "pk": 1055,
    "fields": {
      "event_id": "02144381-4291-45f9-970b-4f293f0c4801",
      "actor_user": null,
      "action": "created",
      "target_table": "learning.LecturerAssignment",
      "target_id": "39",
      "before": {},
      "after": {
        "id": 39,
        "lecturer": 3,
        "unit": 24,
        "academic_year": 2,
        "trimester": 1
      },
      "request_id": "",
      "request_path": "",
      "request_method": "",
      "request_status": null,
      "ip_address": "",
      "user_agent": "",
      "metadata": {},
      "previous_hash": "b91974cb3f1a7542a75300d1e586d1bcfca8c883de3a3af8890dfe73a322b195",
      "integrity_hash": "9f74ef4c413558393904ed971ac20f4581d602c0e9c7f9ad22ea95d296173ab9",
      "created_at": "2026-03-19T07:17:03.558Z"
    }
  },
  {
    "model": "core.auditlog",
    "pk": 1056,
    "fields": {
      "event_id": "3e15f9db-5738-428d-80b8-5953eea01d71",
      "actor_user": null,
      "action": "created",
      "target_table": "finance.FinanceStatus",
      "target_id": "25",
      "before": {},
      "after": {
        "id": 25,
        "student": 13,
        "academic_year": 2,
        "trimester": 1,
        "total_due": "120000.00",
        "total_paid": "90000.00",
        "status": "partial",
        "clearance_status": "cleared_for_registration"
      },
      "request_id": "",
      "request_path": "",
      "request_method": "",
      "request_status": null,
      "ip_address": "",
      "user_agent": "",
      "metadata": {},
      "previous_hash": "9f74ef4c413558393904ed971ac20f4581d602c0e9c7f9ad22ea95d296173ab9",
      "integrity_hash": "bcf601181e69004a47a3aa1733b815ff8ecb9681dc448c0428741501d7f72937",
      "created_at": "2026-03-19T07:17:03.564Z"
    }
  },
  {
    "model": "core.auditlog",
    "pk": 1057,
    "fields": {
      "event_id": "c1a85415-3c21-4876-a3b1-84a26088fdc6",
      "actor_user": null,
      "action": "updated",
      "target_table": "users.Student",
      "target_id": "13",
      "before": {},
      "after": {
        "user": 13,
        "programme": 3,
        "year": 1,
        "trimester": 1,
        "trimester_label": "Year 1, Trimester 1",
        "admission_date": "2026-01-15",
        "current_status": "active",
        "stars": 0
      },
      "request_id": "",
      "request_path": "",
      "request_method": "",
      "request_status": null,
      "ip_address": "",
      "user_agent": "",
      "metadata": {},
      "previous_hash": "bcf601181e69004a47a3aa1733b815ff8ecb9681dc448c0428741501d7f72937",
      "integrity_hash": "088459557872a70adb68937558af51e1053fa772ba2bb15f6bcaea781c49f997",
      "created_at": "2026-03-19T07:17:03.566Z"
    }
  },
  {
    "model": "core.auditlog",
    "pk": 1058,
    "fields": {
      "event_id": "bcb2a1c8-b9ef-468c-adc8-bcb8e27338fa",
      "actor_user": null,
      "action": "created",
      "target_table": "learning.Registration",
      "target_id": "69",
      "before": {},
      "after": {
        "id": 69,
        "student": 15,
        "unit": 22,
        "academic_year": 2,
        "trimester": 1,
        "status": "approved",
        "approved_by": null,
        "approved_at": "2026-03-19T07:17:03.571Z"
      },
      "request_id": "",
      "request_path": "",
      "request_method": "",
      "request_status": null,
      "ip_address": "",
      "user_agent": "",
      "metadata": {},
      "previous_hash": "088459557872a70adb68937558af51e1053fa772ba2bb15f6bcaea781c49f997",
      "integrity_hash": "5f7e94e2b71f57be49cf84b7319aa26067ab149dac5fbbfd854cd8fb569d5abc",
      "created_at": "2026-03-19T07:17:03.572Z"
    }
  },
  {
    "model": "core.auditlog",
    "pk": 1059,
    "fields": {
      "event_id": "e770c670-fb45-4822-979f-fd1b68aeffef",
      "actor_user": null,
      "action": "created",
      "target_table": "learning.Registration",
      "target_id": "70",
      "before": {},
      "after": {
        "id": 70,
        "student": 15,
        "unit": 23,
        "academic_year": 2,
        "trimester": 1,
        "status": "approved",
        "approved_by": null,
        "approved_at": "2026-03-19T07:17:03.578Z"
      },
      "request_id": "",
      "request_path": "",
      "request_method": "",
      "request_status": null,
      "ip_address": "",
      "user_agent": "",
      "metadata": {},
      "previous_hash": "5f7e94e2b71f57be49cf84b7319aa26067ab149dac5fbbfd854cd8fb569d5abc",
      "integrity_hash": "b851c0fe1ace59af4f59ade2d0060ffe995403e41fba08a05687e19e0e1dcdb4",
      "created_at": "2026-03-19T07:17:03.579Z"
    }
  },
  {
    "model": "core.auditlog",
    "pk": 1060,
    "fields": {
      "event_id": "378698a3-e8c2-4875-a19d-ec9c963e23a0",
      "actor_user": null,
      "action": "created",
      "target_table": "learning.Registration",
      "target_id": "71",
      "before": {},
      "after": {
        "id": 71,
        "student": 15,
        "unit": 24,
        "academic_year": 2,
        "trimester": 1,
        "status": "approved",
        "approved_by": null,
        "approved_at": "2026-03-19T07:17:03.581Z"
      },
      "request_id": "",
      "request_path": "",
      "request_method": "",
      "request_status": null,
      "ip_address": "",
      "user_agent": "",
      "metadata": {},
      "previous_hash": "b851c0fe1ace59af4f59ade2d0060ffe995403e41fba08a05687e19e0e1dcdb4",
      "integrity_hash": "13e5a35b64472959c4b012284d834be901cd16b9727e02524f432a9554c05a82",
      "created_at": "2026-03-19T07:17:03.582Z"
    }
  },
  {
    "model": "core.auditlog",
    "pk": 1061,
    "fields": {
      "event_id": "fd9e01ca-10ca-43e5-8b2a-20d91b985e8c",
      "actor_user": null,
      "action": "created",
      "target_table": "communications.Thread",
      "target_id": "29",
      "before": {},
      "after": {
        "id": 29,
        "subject": "TT-211 lecturer channel",
        "student": 15,
        "teacher": 3,
        "parent": null
      },
      "request_id": "",
      "request_path": "",
      "request_method": "",
      "request_status": null,
      "ip_address": "",
      "user_agent": "",
      "metadata": {},
      "previous_hash": "13e5a35b64472959c4b012284d834be901cd16b9727e02524f432a9554c05a82",
      "integrity_hash": "1b326157687b64a6d18d8dd7742ce401f581ac29c4edec998e26fa5bd027f6eb",
      "created_at": "2026-03-19T07:17:03.588Z"
    }
  },
  {
    "model": "core.auditlog",
    "pk": 1062,
    "fields": {
      "event_id": "41b492ba-6e7f-4b23-b88a-13e9859e814e",
      "actor_user": null,
      "action": "created",
      "target_table": "communications.Thread",
      "target_id": "30",
      "before": {},
      "after": {
        "id": 30,
        "subject": "TT-211 guardian channel",
        "student": 15,
        "teacher": 3,
        "parent": 16
      },
      "request_id": "",
      "request_path": "",
      "request_method": "",
      "request_status": null,
      "ip_address": "",
      "user_agent": "",
      "metadata": {},
      "previous_hash": "1b326157687b64a6d18d8dd7742ce401f581ac29c4edec998e26fa5bd027f6eb",
      "integrity_hash": "55b4bf40107ba63f9db5f01fe4c2d1c9a811f9ed19da902e687101601546431c",
      "created_at": "2026-03-19T07:17:03.591Z"
    }
  },
  {
    "model": "core.auditlog",
    "pk": 1063,
    "fields": {
      "event_id": "9bafeaaf-6a4a-4363-b02d-8f2ccff9f2b9",
      "actor_user": null,
      "action": "created",
      "target_table": "finance.FinanceStatus",
      "target_id": "26",
      "before": {},
      "after": {
        "id": 26,
        "student": 15,
        "academic_year": 2,
        "trimester": 1,
        "total_due": "120000.00",
        "total_paid": "90000.00",
        "status": "partial",
        "clearance_status": "cleared_for_registration"
      },
      "request_id": "",
      "request_path": "",
      "request_method": "",
      "request_status": null,
      "ip_address": "",
      "user_agent": "",
      "metadata": {},
      "previous_hash": "55b4bf40107ba63f9db5f01fe4c2d1c9a811f9ed19da902e687101601546431c",
      "integrity_hash": "94822b895465ba5c13618002703195035bc88a6af363d78a434515a1ed818078",
      "created_at": "2026-03-19T07:17:03.606Z"
    }
  },
  {
    "model": "core.auditlog",
    "pk": 1064,
    "fields": {
      "event_id": "017314d7-8c4c-4b1f-bf15-673f8919fc88",
      "actor_user": null,
      "action": "updated",
      "target_table": "users.Student",
      "target_id": "15",
      "before": {},
      "after": {
        "user": 15,
        "programme": 3,
        "year": 1,
        "trimester": 1,
        "trimester_label": "Year 1, Trimester 1",
        "admission_date": "2026-03-12",
        "current_status": "active",
        "stars": 0
      },
      "request_id": "",
      "request_path": "",
      "request_method": "",
      "request_status": null,
      "ip_address": "",
      "user_agent": "",
      "metadata": {},
      "previous_hash": "94822b895465ba5c13618002703195035bc88a6af363d78a434515a1ed818078",
      "integrity_hash": "d034407939f717f4fdf5ec22a28856b5b8887188d5ef4076a9a3a42f956dfd0b",
      "created_at": "2026-03-19T07:17:03.610Z"
    }
  },
  {
    "model": "core.auditlog",
    "pk": 1065,
    "fields": {
      "event_id": "b92e8ae4-17c1-4f47-9022-e4405947000e",
      "actor_user": null,
      "action": "created",
      "target_table": "learning.Registration",
      "target_id": "72",
      "before": {},
      "after": {
        "id": 72,
        "student": 17,
        "unit": 22,
        "academic_year": 2,
        "trimester": 1,
        "status": "approved",
        "approved_by": null,
        "approved_at": "2026-03-19T07:17:03.615Z"
      },
      "request_id": "",
      "request_path": "",
      "request_method": "",
      "request_status": null,
      "ip_address": "",
      "user_agent": "",
      "metadata": {},
      "previous_hash": "d034407939f717f4fdf5ec22a28856b5b8887188d5ef4076a9a3a42f956dfd0b",
      "integrity_hash": "961fcb7c89d7d3f4ec66db57e49bfb0cdf5417fd6cf1244cf9b37f2abeec080b",
      "created_at": "2026-03-19T07:17:03.616Z"
    }
  },
  {
    "model": "core.auditlog",
    "pk": 1066,
    "fields": {
      "event_id": "fb86a489-a615-418a-9e06-8b265fa4f2ca",
      "actor_user": null,
      "action": "created",
      "target_table": "learning.Registration",
      "target_id": "73",
      "before": {},
      "after": {
        "id": 73,
        "student": 17,
        "unit": 23,
        "academic_year": 2,
        "trimester": 1,
        "status": "approved",
        "approved_by": null,
        "approved_at": "2026-03-19T07:17:03.619Z"
      },
      "request_id": "",
      "request_path": "",
      "request_method": "",
      "request_status": null,
      "ip_address": "",
      "user_agent": "",
      "metadata": {},
      "previous_hash": "961fcb7c89d7d3f4ec66db57e49bfb0cdf5417fd6cf1244cf9b37f2abeec080b",
      "integrity_hash": "a5fed319ccd05e571b2f092d554fdb4e3ff431febe723e6c86021930e2125623",
      "created_at": "2026-03-19T07:17:03.621Z"
    }
  },
  {
    "model": "core.auditlog",
    "pk": 1067,
    "fields": {
      "event_id": "03c19145-513b-43c7-b244-578161070033",
      "actor_user": null,
      "action": "created",
      "target_table": "learning.Registration",
      "target_id": "74",
      "before": {},
      "after": {
        "id": 74,
        "student": 17,
        "unit": 24,
        "academic_year": 2,
        "trimester": 1,
        "status": "approved",
        "approved_by": null,
        "approved_at": "2026-03-19T07:17:03.624Z"
      },
      "request_id": "",
      "request_path": "",
      "request_method": "",
      "request_status": null,
      "ip_address": "",
      "user_agent": "",
      "metadata": {},
      "previous_hash": "a5fed319ccd05e571b2f092d554fdb4e3ff431febe723e6c86021930e2125623",
      "integrity_hash": "961ff9582aaae044674482727cb9960bf880ce82b3c203021417175d9c201d66",
      "created_at": "2026-03-19T07:17:03.625Z"
    }
  },
  {
    "model": "core.auditlog",
    "pk": 1068,
    "fields": {
      "event_id": "690b1313-4a6e-450e-a964-7ca350fff13a",
      "actor_user": null,
      "action": "created",
      "target_table": "communications.Thread",
      "target_id": "31",
      "before": {},
      "after": {
        "id": 31,
        "subject": "TT-211 lecturer channel",
        "student": 17,
        "teacher": 3,
        "parent": null
      },
      "request_id": "",
      "request_path": "",
      "request_method": "",
      "request_status": null,
      "ip_address": "",
      "user_agent": "",
      "metadata": {},
      "previous_hash": "961ff9582aaae044674482727cb9960bf880ce82b3c203021417175d9c201d66",
      "integrity_hash": "ac0581dd8a52ced9f7688fa4189fd1df3b80a3138d07adb43bdc223ea4e505ad",
      "created_at": "2026-03-19T07:17:03.630Z"
    }
  },
  {
    "model": "core.auditlog",
    "pk": 1069,
    "fields": {
      "event_id": "cd1a0c5e-9777-4563-b42e-5297b17bc3e8",
      "actor_user": null,
      "action": "created",
      "target_table": "communications.Thread",
      "target_id": "32",
      "before": {},
      "after": {
        "id": 32,
        "subject": "TT-211 guardian channel",
        "student": 17,
        "teacher": 3,
        "parent": 18
      },
      "request_id": "",
      "request_path": "",
      "request_method": "",
      "request_status": null,
      "ip_address": "",
      "user_agent": "",
      "metadata": {},
      "previous_hash": "ac0581dd8a52ced9f7688fa4189fd1df3b80a3138d07adb43bdc223ea4e505ad",
      "integrity_hash": "7b0cce8dc7a53bb75051c13bf07d44927fca792fb99675755309bdd0b95007f1",
      "created_at": "2026-03-19T07:17:03.633Z"
    }
  },
  {
    "model": "core.auditlog",
    "pk": 1070,
    "fields": {
      "event_id": "e613a8b2-5f61-441c-a348-227fadac54dd",
      "actor_user": null,
      "action": "created",
      "target_table": "finance.FinanceStatus",
      "target_id": "27",
      "before": {},
      "after": {
        "id": 27,
        "student": 17,
        "academic_year": 2,
        "trimester": 1,
        "total_due": "120000.00",
        "total_paid": "90000.00",
        "status": "partial",
        "clearance_status": "cleared_for_registration"
      },
      "request_id": "",
      "request_path": "",
      "request_method": "",
      "request_status": null,
      "ip_address": "",
      "user_agent": "",
      "metadata": {},
      "previous_hash": "7b0cce8dc7a53bb75051c13bf07d44927fca792fb99675755309bdd0b95007f1",
      "integrity_hash": "19f0431979c7ab910e158312503ce2c3b413d3187e0fffe4e0b8b219cd8ae545",
      "created_at": "2026-03-19T07:17:03.642Z"
    }
  },
  {
    "model": "core.auditlog",
    "pk": 1071,
    "fields": {
      "event_id": "71f8d209-0c23-475b-88b9-84d337d7f1b6",
      "actor_user": null,
      "action": "updated",
      "target_table": "users.Student",
      "target_id": "17",
      "before": {},
      "after": {
        "user": 17,
        "programme": 3,
        "year": 1,
        "trimester": 1,
        "trimester_label": "Year 1, Trimester 1",
        "admission_date": "2026-03-12",
        "current_status": "active",
        "stars": 0
      },
      "request_id": "",
      "request_path": "",
      "request_method": "",
      "request_status": null,
      "ip_address": "",
      "user_agent": "",
      "metadata": {},
      "previous_hash": "19f0431979c7ab910e158312503ce2c3b413d3187e0fffe4e0b8b219cd8ae545",
      "integrity_hash": "9ad1c000d9b4ff7692bb5eade7e6e46727e875b021caa34516cd4f756bdeaa59",
      "created_at": "2026-03-19T07:17:03.644Z"
    }
  },
  {
    "model": "core.auditlog",
    "pk": 1072,
    "fields": {
      "event_id": "c2196c61-d5d9-42e7-b9ef-9e1a43895607",
      "actor_user": null,
      "action": "created",
      "target_table": "learning.Registration",
      "target_id": "75",
      "before": {},
      "after": {
        "id": 75,
        "student": 19,
        "unit": 22,
        "academic_year": 2,
        "trimester": 1,
        "status": "approved",
        "approved_by": null,
        "approved_at": "2026-03-19T07:17:03.648Z"
      },
      "request_id": "",
      "request_path": "",
      "request_method": "",
      "request_status": null,
      "ip_address": "",
      "user_agent": "",
      "metadata": {},
      "previous_hash": "9ad1c000d9b4ff7692bb5eade7e6e46727e875b021caa34516cd4f756bdeaa59",
      "integrity_hash": "54fafc8150767d3706dd940cbfe80aad22ea57547a2b1c9ffdf8794340c1a443",
      "created_at": "2026-03-19T07:17:03.650Z"
    }
  },
  {
    "model": "core.auditlog",
    "pk": 1073,
    "fields": {
      "event_id": "aefa1bee-32f9-4a00-8e5b-15e9c577cfa3",
      "actor_user": null,
      "action": "created",
      "target_table": "learning.Registration",
      "target_id": "76",
      "before": {},
      "after": {
        "id": 76,
        "student": 19,
        "unit": 23,
        "academic_year": 2,
        "trimester": 1,
        "status": "approved",
        "approved_by": null,
        "approved_at": "2026-03-19T07:17:03.653Z"
      },
      "request_id": "",
      "request_path": "",
      "request_method": "",
      "request_status": null,
      "ip_address": "",
      "user_agent": "",
      "metadata": {},
      "previous_hash": "54fafc8150767d3706dd940cbfe80aad22ea57547a2b1c9ffdf8794340c1a443",
      "integrity_hash": "16ee163a267bfb9fd8955fcda1c6a2d929f8eadfca4922adf8f384e2ffbf1c22",
      "created_at": "2026-03-19T07:17:03.655Z"
    }
  },
  {
    "model": "core.auditlog",
    "pk": 1074,
    "fields": {
      "event_id": "306ef817-984e-4698-b261-0d426a4cae8b",
      "actor_user": null,
      "action": "created",
      "target_table": "learning.Registration",
      "target_id": "77",
      "before": {},
      "after": {
        "id": 77,
        "student": 19,
        "unit": 24,
        "academic_year": 2,
        "trimester": 1,
        "status": "approved",
        "approved_by": null,
        "approved_at": "2026-03-19T07:17:03.657Z"
      },
      "request_id": "",
      "request_path": "",
      "request_method": "",
      "request_status": null,
      "ip_address": "",
      "user_agent": "",
      "metadata": {},
      "previous_hash": "16ee163a267bfb9fd8955fcda1c6a2d929f8eadfca4922adf8f384e2ffbf1c22",
      "integrity_hash": "d4eb75d6fe468899ef21b4e2e6912cae546715d7149bcac59131484e486fbd0f",
      "created_at": "2026-03-19T07:17:03.659Z"
    }
  },
  {
    "model": "core.auditlog",
    "pk": 1075,
    "fields": {
      "event_id": "ae457668-04cd-49b4-8c8d-3ea322286551",
      "actor_user": null,
      "action": "created",
      "target_table": "communications.Thread",
      "target_id": "33",
      "before": {},
      "after": {
        "id": 33,
        "subject": "TT-211 lecturer channel",
        "student": 19,
        "teacher": 3,
        "parent": null
      },
      "request_id": "",
      "request_path": "",
      "request_method": "",
      "request_status": null,
      "ip_address": "",
      "user_agent": "",
      "metadata": {},
      "previous_hash": "d4eb75d6fe468899ef21b4e2e6912cae546715d7149bcac59131484e486fbd0f",
      "integrity_hash": "85ed4f9aa6859e305d4d3e9b01278384e8f07ac2053c7137e22747bda73fa671",
      "created_at": "2026-03-19T07:17:03.665Z"
    }
  },
  {
    "model": "core.auditlog",
    "pk": 1076,
    "fields": {
      "event_id": "d0e26e8b-f16d-4ed3-98d9-ebaec81bd673",
      "actor_user": null,
      "action": "created",
      "target_table": "communications.Thread",
      "target_id": "34",
      "before": {},
      "after": {
        "id": 34,
        "subject": "TT-211 guardian channel",
        "student": 19,
        "teacher": 3,
        "parent": 20
      },
      "request_id": "",
      "request_path": "",
      "request_method": "",
      "request_status": null,
      "ip_address": "",
      "user_agent": "",
      "metadata": {},
      "previous_hash": "85ed4f9aa6859e305d4d3e9b01278384e8f07ac2053c7137e22747bda73fa671",
      "integrity_hash": "cad1e8be8c2b77791e771c7b166756b6104a53ee64247aab9ef827a480d692c1",
      "created_at": "2026-03-19T07:17:03.668Z"
    }
  },
  {
    "model": "core.auditlog",
    "pk": 1077,
    "fields": {
      "event_id": "cda8aaa8-bffb-449a-afd7-5f43871d007f",
      "actor_user": null,
      "action": "created",
      "target_table": "finance.FinanceStatus",
      "target_id": "28",
      "before": {},
      "after": {
        "id": 28,
        "student": 19,
        "academic_year": 2,
        "trimester": 1,
        "total_due": "120000.00",
        "total_paid": "90000.00",
        "status": "partial",
        "clearance_status": "cleared_for_registration"
      },
      "request_id": "",
      "request_path": "",
      "request_method": "",
      "request_status": null,
      "ip_address": "",
      "user_agent": "",
      "metadata": {},
      "previous_hash": "cad1e8be8c2b77791e771c7b166756b6104a53ee64247aab9ef827a480d692c1",
      "integrity_hash": "84ffe8fcbfc397f209b8a645f29f477196f1fab0c173e14680d80d0c2f7794be",
      "created_at": "2026-03-19T07:17:03.679Z"
    }
  },
  {
    "model": "core.auditlog",
    "pk": 1078,
    "fields": {
      "event_id": "b27302ff-fbeb-4621-bc80-486a05ec0e38",
      "actor_user": null,
      "action": "updated",
      "target_table": "users.Student",
      "target_id": "19",
      "before": {},
      "after": {
        "user": 19,
        "programme": 3,
        "year": 1,
        "trimester": 1,
        "trimester_label": "Year 1, Trimester 1",
        "admission_date": "2026-03-12",
        "current_status": "active",
        "stars": 0
      },
      "request_id": "",
      "request_path": "",
      "request_method": "",
      "request_status": null,
      "ip_address": "",
      "user_agent": "",
      "metadata": {},
      "previous_hash": "84ffe8fcbfc397f209b8a645f29f477196f1fab0c173e14680d80d0c2f7794be",
      "integrity_hash": "a35fe5bd7ea67993a296efebd342b77647763b668295072b34950bdda1dfc0fd",
      "created_at": "2026-03-19T07:17:03.681Z"
    }
  },
  {
    "model": "core.auditlog",
    "pk": 1079,
    "fields": {
      "event_id": "dafb8bed-ebe0-41bc-876a-d3986a6c25b3",
      "actor_user": null,
      "action": "created",
      "target_table": "learning.LecturerAssignment",
      "target_id": "40",
      "before": {},
      "after": {
        "id": 40,
        "lecturer": 3,
        "unit": 10,
        "academic_year": 2,
        "trimester": 1
      },
      "request_id": "",
      "request_path": "",
      "request_method": "",
      "request_status": null,
      "ip_address": "",
      "user_agent": "",
      "metadata": {},
      "previous_hash": "a35fe5bd7ea67993a296efebd342b77647763b668295072b34950bdda1dfc0fd",
      "integrity_hash": "33399ba20009359082c014b27acc99779f5fb5ae18c18aa60e0bdfd2ba23a897",
      "created_at": "2026-03-19T07:17:03.689Z"
    }
  },
  {
    "model": "core.auditlog",
    "pk": 1080,
    "fields": {
      "event_id": "8e464783-5bfb-4ec9-a8ed-427929f6163a",
      "actor_user": null,
      "action": "created",
      "target_table": "communications.Thread",
      "target_id": "35",
      "before": {},
      "after": {
        "id": 35,
        "subject": "TT-111 lecturer channel",
        "student": 21,
        "teacher": 3,
        "parent": null
      },
      "request_id": "",
      "request_path": "",
      "request_method": "",
      "request_status": null,
      "ip_address": "",
      "user_agent": "",
      "metadata": {},
      "previous_hash": "33399ba20009359082c014b27acc99779f5fb5ae18c18aa60e0bdfd2ba23a897",
      "integrity_hash": "3534297c939a4222e8a53743efd1cc60be570b21f880d5c9033873b826661e5d",
      "created_at": "2026-03-19T07:17:03.693Z"
    }
  },
  {
    "model": "core.auditlog",
    "pk": 1081,
    "fields": {
      "event_id": "e811ca4a-c05a-4b41-9586-67c186a700c7",
      "actor_user": null,
      "action": "created",
      "target_table": "communications.Thread",
      "target_id": "36",
      "before": {},
      "after": {
        "id": 36,
        "subject": "TT-111 guardian channel",
        "student": 21,
        "teacher": 3,
        "parent": 22
      },
      "request_id": "",
      "request_path": "",
      "request_method": "",
      "request_status": null,
      "ip_address": "",
      "user_agent": "",
      "metadata": {},
      "previous_hash": "3534297c939a4222e8a53743efd1cc60be570b21f880d5c9033873b826661e5d",
      "integrity_hash": "aad2448ec7924a5bb5adc732965c7a6cdc01f0023214151b3e6c5676edeb28b0",
      "created_at": "2026-03-19T07:17:03.696Z"
    }
  },
  {
    "model": "core.auditlog",
    "pk": 1082,
    "fields": {
      "event_id": "a7f2dc85-9eb8-4516-a796-a9dff0d7e90a",
      "actor_user": null,
      "action": "created",
      "target_table": "learning.LecturerAssignment",
      "target_id": "41",
      "before": {},
      "after": {
        "id": 41,
        "lecturer": 3,
        "unit": 11,
        "academic_year": 2,
        "trimester": 1
      },
      "request_id": "",
      "request_path": "",
      "request_method": "",
      "request_status": null,
      "ip_address": "",
      "user_agent": "",
      "metadata": {},
      "previous_hash": "aad2448ec7924a5bb5adc732965c7a6cdc01f0023214151b3e6c5676edeb28b0",
      "integrity_hash": "da979ac550715666abf4e5c8ab39bf21d4a6e61079468dbeba153fefc3a47c43",
      "created_at": "2026-03-19T07:17:03.706Z"
    }
  },
  {
    "model": "core.auditlog",
    "pk": 1083,
    "fields": {
      "event_id": "ff950319-f5f4-41e5-9e91-036c1e3089a2",
      "actor_user": null,
      "action": "created",
      "target_table": "learning.LecturerAssignment",
      "target_id": "42",
      "before": {},
      "after": {
        "id": 42,
        "lecturer": 3,
        "unit": 12,
        "academic_year": 2,
        "trimester": 1
      },
      "request_id": "",
      "request_path": "",
      "request_method": "",
      "request_status": null,
      "ip_address": "",
      "user_agent": "",
      "metadata": {},
      "previous_hash": "da979ac550715666abf4e5c8ab39bf21d4a6e61079468dbeba153fefc3a47c43",
      "integrity_hash": "378806a558808adaff39d15fff0d2e453a771518c028b45506f74d10629d1d79",
      "created_at": "2026-03-19T07:17:03.720Z"
    }
  },
  {
    "model": "core.auditlog",
    "pk": 1084,
    "fields": {
      "event_id": "9c5d2b72-5cdf-4dda-9485-a446a6512292",
      "actor_user": null,
      "action": "updated",
      "target_table": "finance.FinanceStatus",
      "target_id": "6",
      "before": {},
      "after": {
        "id": 6,
        "student": 21,
        "academic_year": 2,
        "trimester": 1,
        "total_due": "120000.00",
        "total_paid": "90000.00",
        "status": "partial",
        "clearance_status": "cleared_for_registration"
      },
      "request_id": "",
      "request_path": "",
      "request_method": "",
      "request_status": null,
      "ip_address": "",
      "user_agent": "",
      "metadata": {},
      "previous_hash": "378806a558808adaff39d15fff0d2e453a771518c028b45506f74d10629d1d79",
      "integrity_hash": "f6dc81d6c33d3072b60e13b82dba575483630e45d39e234ba6d1e871a484edc2",
      "created_at": "2026-03-19T07:17:03.726Z"
    }
  },
  {
    "model": "core.auditlog",
    "pk": 1085,
    "fields": {
      "event_id": "4b82e249-9ecd-4d66-ab7f-d1b9babb7f24",
      "actor_user": null,
      "action": "updated",
      "target_table": "users.Student",
      "target_id": "21",
      "before": {},
      "after": {
        "user": 21,
        "programme": 3,
        "year": 2,
        "trimester": 1,
        "trimester_label": "Year 2, Trimester 1",
        "admission_date": "2026-03-12",
        "current_status": "active",
        "stars": 0
      },
      "request_id": "",
      "request_path": "",
      "request_method": "",
      "request_status": null,
      "ip_address": "",
      "user_agent": "",
      "metadata": {},
      "previous_hash": "f6dc81d6c33d3072b60e13b82dba575483630e45d39e234ba6d1e871a484edc2",
      "integrity_hash": "d334fe35e301a13b4cb80b83f219c2d602c1a30d608b489663d9ff7e33981e6d",
      "created_at": "2026-03-19T07:17:03.728Z"
    }
  },
  {
    "model": "core.auditlog",
    "pk": 1086,
    "fields": {
      "event_id": "eae2ff15-b57e-47a3-9a61-5387df56c114",
      "actor_user": null,
      "action": "created",
      "target_table": "communications.Thread",
      "target_id": "37",
      "before": {},
      "after": {
        "id": 37,
        "subject": "TT-111 lecturer channel",
        "student": 23,
        "teacher": 3,
        "parent": null
      },
      "request_id": "",
      "request_path": "",
      "request_method": "",
      "request_status": null,
      "ip_address": "",
      "user_agent": "",
      "metadata": {},
      "previous_hash": "d334fe35e301a13b4cb80b83f219c2d602c1a30d608b489663d9ff7e33981e6d",
      "integrity_hash": "dc4a7c951eff837b5f14177b2fe2b35ea8f150bf07c7bc35f50417426c57dd78",
      "created_at": "2026-03-19T07:17:03.737Z"
    }
  },
  {
    "model": "core.auditlog",
    "pk": 1087,
    "fields": {
      "event_id": "02c95d33-13ad-4712-8de1-b26e194e9dc4",
      "actor_user": null,
      "action": "created",
      "target_table": "communications.Thread",
      "target_id": "38",
      "before": {},
      "after": {
        "id": 38,
        "subject": "TT-111 guardian channel",
        "student": 23,
        "teacher": 3,
        "parent": 24
      },
      "request_id": "",
      "request_path": "",
      "request_method": "",
      "request_status": null,
      "ip_address": "",
      "user_agent": "",
      "metadata": {},
      "previous_hash": "dc4a7c951eff837b5f14177b2fe2b35ea8f150bf07c7bc35f50417426c57dd78",
      "integrity_hash": "0aa7b8deb074bd2bd10e1f26f25e8d6b48c97373da36aa7442032e29f298401f",
      "created_at": "2026-03-19T07:17:03.740Z"
    }
  },
  {
    "model": "core.auditlog",
    "pk": 1088,
    "fields": {
      "event_id": "3e4e832a-9c40-479d-b5f0-8a85c9a111a7",
      "actor_user": null,
      "action": "updated",
      "target_table": "finance.FinanceStatus",
      "target_id": "7",
      "before": {},
      "after": {
        "id": 7,
        "student": 23,
        "academic_year": 2,
        "trimester": 1,
        "total_due": "120000.00",
        "total_paid": "90000.00",
        "status": "partial",
        "clearance_status": "cleared_for_registration"
      },
      "request_id": "",
      "request_path": "",
      "request_method": "",
      "request_status": null,
      "ip_address": "",
      "user_agent": "",
      "metadata": {},
      "previous_hash": "0aa7b8deb074bd2bd10e1f26f25e8d6b48c97373da36aa7442032e29f298401f",
      "integrity_hash": "27383a493636991b22a6b490fecc4c865152106637fbe14d806bacad707aa36e",
      "created_at": "2026-03-19T07:17:03.751Z"
    }
  },
  {
    "model": "core.auditlog",
    "pk": 1089,
    "fields": {
      "event_id": "534c35d3-dfa2-4ff8-beba-d40b042ab294",
      "actor_user": null,
      "action": "updated",
      "target_table": "users.Student",
      "target_id": "23",
      "before": {},
      "after": {
        "user": 23,
        "programme": 3,
        "year": 2,
        "trimester": 1,
        "trimester_label": "Year 2, Trimester 1",
        "admission_date": "2026-03-12",
        "current_status": "active",
        "stars": 0
      },
      "request_id": "",
      "request_path": "",
      "request_method": "",
      "request_status": null,
      "ip_address": "",
      "user_agent": "",
      "metadata": {},
      "previous_hash": "27383a493636991b22a6b490fecc4c865152106637fbe14d806bacad707aa36e",
      "integrity_hash": "2afb875a5dd30c85efb29f9edc35c6ff5906d6f6f99065b64b97228e309e772d",
      "created_at": "2026-03-19T07:17:03.753Z"
    }
  },
  {
    "model": "core.auditlog",
    "pk": 1090,
    "fields": {
      "event_id": "5868385e-beb2-45b8-9afd-d449556cb97c",
      "actor_user": null,
      "action": "created",
      "target_table": "communications.Thread",
      "target_id": "39",
      "before": {},
      "after": {
        "id": 39,
        "subject": "TT-111 lecturer channel",
        "student": 25,
        "teacher": 3,
        "parent": null
      },
      "request_id": "",
      "request_path": "",
      "request_method": "",
      "request_status": null,
      "ip_address": "",
      "user_agent": "",
      "metadata": {},
      "previous_hash": "2afb875a5dd30c85efb29f9edc35c6ff5906d6f6f99065b64b97228e309e772d",
      "integrity_hash": "b887bc88e0593441da325c957bc66d3f4bb1105b619471a336eb582e57e3f703",
      "created_at": "2026-03-19T07:17:03.765Z"
    }
  },
  {
    "model": "core.auditlog",
    "pk": 1091,
    "fields": {
      "event_id": "8932ae82-726b-4265-a11e-a86a01217aab",
      "actor_user": null,
      "action": "created",
      "target_table": "communications.Thread",
      "target_id": "40",
      "before": {},
      "after": {
        "id": 40,
        "subject": "TT-111 guardian channel",
        "student": 25,
        "teacher": 3,
        "parent": 26
      },
      "request_id": "",
      "request_path": "",
      "request_method": "",
      "request_status": null,
      "ip_address": "",
      "user_agent": "",
      "metadata": {},
      "previous_hash": "b887bc88e0593441da325c957bc66d3f4bb1105b619471a336eb582e57e3f703",
      "integrity_hash": "123c7bb98e2d7ad7adc5d44c791afd01d813a46a1590bf3f20119b111540ddf6",
      "created_at": "2026-03-19T07:17:03.767Z"
    }
  },
  {
    "model": "core.auditlog",
    "pk": 1092,
    "fields": {
      "event_id": "355b361d-593f-438c-b7d1-155af0ea6fc6",
      "actor_user": null,
      "action": "updated",
      "target_table": "finance.FinanceStatus",
      "target_id": "8",
      "before": {},
      "after": {
        "id": 8,
        "student": 25,
        "academic_year": 2,
        "trimester": 1,
        "total_due": "120000.00",
        "total_paid": "90000.00",
        "status": "partial",
        "clearance_status": "cleared_for_registration"
      },
      "request_id": "",
      "request_path": "",
      "request_method": "",
      "request_status": null,
      "ip_address": "",
      "user_agent": "",
      "metadata": {},
      "previous_hash": "123c7bb98e2d7ad7adc5d44c791afd01d813a46a1590bf3f20119b111540ddf6",
      "integrity_hash": "5af40eb8d30240bcc5db4613002577d04d84b9a5e999e6bb40a18257d89a3411",
      "created_at": "2026-03-19T07:17:03.782Z"
    }
  },
  {
    "model": "core.auditlog",
    "pk": 1093,
    "fields": {
      "event_id": "0a2f3b81-5bc2-4d03-b03a-ce4e7af18199",
      "actor_user": null,
      "action": "updated",
      "target_table": "users.Student",
      "target_id": "25",
      "before": {},
      "after": {
        "user": 25,
        "programme": 3,
        "year": 2,
        "trimester": 1,
        "trimester_label": "Year 2, Trimester 1",
        "admission_date": "2026-03-12",
        "current_status": "active",
        "stars": 0
      },
      "request_id": "",
      "request_path": "",
      "request_method": "",
      "request_status": null,
      "ip_address": "",
      "user_agent": "",
      "metadata": {},
      "previous_hash": "5af40eb8d30240bcc5db4613002577d04d84b9a5e999e6bb40a18257d89a3411",
      "integrity_hash": "bba69d313478a52a754eef6c4d5420c7f286414b67a4759d17da3a947871b27b",
      "created_at": "2026-03-19T07:17:03.785Z"
    }
  },
  {
    "model": "core.auditlog",
    "pk": 1094,
    "fields": {
      "event_id": "ba4cdc09-9e1e-4b06-b8e1-12b9903a7aa8",
      "actor_user": null,
      "action": "updated",
      "target_table": "learning.Registration",
      "target_id": "69",
      "before": {},
      "after": {
        "id": 69,
        "student": 15,
        "unit": 22,
        "academic_year": 2,
        "trimester": 1,
        "status": "pending_hod",
        "approved_by": null,
        "approved_at": null
      },
      "request_id": "",
      "request_path": "",
      "request_method": "",
      "request_status": null,
      "ip_address": "",
      "user_agent": "",
      "metadata": {},
      "previous_hash": "bba69d313478a52a754eef6c4d5420c7f286414b67a4759d17da3a947871b27b",
      "integrity_hash": "9bd8524142fbdee526ac02aadda1d255fe54432aaef22c5dc184904776b8da83",
      "created_at": "2026-03-19T07:17:03.797Z"
    }
  },
  {
    "model": "core.auditlog",
    "pk": 1095,
    "fields": {
      "event_id": "4cd61293-87c9-423b-88c5-19f6f128944a",
      "actor_user": null,
      "action": "updated",
      "target_table": "learning.Registration",
      "target_id": "69",
      "before": {},
      "after": {
        "id": 69,
        "student": 15,
        "unit": 22,
        "academic_year": 2,
        "trimester": 1,
        "status": "pending_hod",
        "approved_by": null,
        "approved_at": null
      },
      "request_id": "",
      "request_path": "",
      "request_method": "",
      "request_status": null,
      "ip_address": "",
      "user_agent": "",
      "metadata": {},
      "previous_hash": "9bd8524142fbdee526ac02aadda1d255fe54432aaef22c5dc184904776b8da83",
      "integrity_hash": "c0709eff744c871798312dff43bf31872263a31751c191c4554bb8bef673902c",
      "created_at": "2026-03-19T07:17:03.800Z"
    }
  },
  {
    "model": "core.auditlog",
    "pk": 1096,
    "fields": {
      "event_id": "187354ea-3f85-4ff0-acf7-5529a07cad50",
      "actor_user": null,
      "action": "updated",
      "target_table": "learning.Registration",
      "target_id": "70",
      "before": {},
      "after": {
        "id": 70,
        "student": 15,
        "unit": 23,
        "academic_year": 2,
        "trimester": 1,
        "status": "pending_hod",
        "approved_by": null,
        "approved_at": null
      },
      "request_id": "",
      "request_path": "",
      "request_method": "",
      "request_status": null,
      "ip_address": "",
      "user_agent": "",
      "metadata": {},
      "previous_hash": "c0709eff744c871798312dff43bf31872263a31751c191c4554bb8bef673902c",
      "integrity_hash": "69e8741c6733eae26974f209b686bfdc85b049fa09b976eb5111063b774f5feb",
      "created_at": "2026-03-19T07:17:03.813Z"
    }
  },
  {
    "model": "core.auditlog",
    "pk": 1097,
    "fields": {
      "event_id": "d6a6e815-4256-4531-9536-740f9d4459d3",
      "actor_user": null,
      "action": "updated",
      "target_table": "learning.Registration",
      "target_id": "70",
      "before": {},
      "after": {
        "id": 70,
        "student": 15,
        "unit": 23,
        "academic_year": 2,
        "trimester": 1,
        "status": "pending_hod",
        "approved_by": null,
        "approved_at": null
      },
      "request_id": "",
      "request_path": "",
      "request_method": "",
      "request_status": null,
      "ip_address": "",
      "user_agent": "",
      "metadata": {},
      "previous_hash": "69e8741c6733eae26974f209b686bfdc85b049fa09b976eb5111063b774f5feb",
      "integrity_hash": "dce176d7b4466c008ec076b9a107b449503d886451de77054207a5cfa9b9caea",
      "created_at": "2026-03-19T07:17:03.816Z"
    }
  },
  {
    "model": "core.auditlog",
    "pk": 1098,
    "fields": {
      "event_id": "dc957316-88e5-43d1-9b87-3cd24e9581e7",
      "actor_user": null,
      "action": "updated",
      "target_table": "users.Student",
      "target_id": "15",
      "before": {},
      "after": {
        "user": 15,
        "programme": 3,
        "year": 1,
        "trimester": 1,
        "trimester_label": "Year 1, Trimester 1",
        "admission_date": "2026-03-12",
        "current_status": "pending_hod",
        "stars": 0
      },
      "request_id": "",
      "request_path": "",
      "request_method": "",
      "request_status": null,
      "ip_address": "",
      "user_agent": "",
      "metadata": {},
      "previous_hash": "dce176d7b4466c008ec076b9a107b449503d886451de77054207a5cfa9b9caea",
      "integrity_hash": "ae42c5be76be3f4b6fc77a4faeeb092a77a111025ddfd1732d25c89943295f00",
      "created_at": "2026-03-19T07:17:03.825Z"
    }
  },
  {
    "model": "core.auditlog",
    "pk": 1099,
    "fields": {
      "event_id": "4813f5c5-e2c6-4fca-92d5-c4fe9b2737f7",
      "actor_user": null,
      "action": "updated",
      "target_table": "users.User",
      "target_id": "5",
      "before": {},
      "after": {
        "id": 5,
        "password": "pbkdf2_sha256$1000000$L0K5fCEyCTFT4Pd8awN2eK$s/m66DzMKfQ6zSoF/ZdbHbdAx80KY4AEDLKu4fFzb08=",
        "last_login": "2026-03-19T07:18:40.518Z",
        "is_superuser": false,
        "username": "student1",
        "first_name": "",
        "last_name": "",
        "email": "student1@example.com",
        "is_staff": false,
        "is_active": true,
        "date_joined": "2025-11-19T11:28:49.438Z",
        "role": "student",
        "display_name": "Aisha Student",
        "phone": "",
        "date_of_birth": null,
        "address": "",
        "must_change_password": false,
        "prefers_simple_language": true,
        "prefers_high_contrast": false,
        "speech_rate": 0.9,
        "totp_secret": "",
        "totp_enabled": false,
        "totp_activated_at": null,
        "groups": [],
        "user_permissions": []
      },
      "request_id": "",
      "request_path": "",
      "request_method": "",
      "request_status": null,
      "ip_address": "",
      "user_agent": "",
      "metadata": {},
      "previous_hash": "ae42c5be76be3f4b6fc77a4faeeb092a77a111025ddfd1732d25c89943295f00",
      "integrity_hash": "64137574a72fb8b5b1d461d1ff3f60415aab5140a4186caec71e86a255fa2891",
      "created_at": "2026-03-19T07:18:40.530Z"
    }
  },
  {
    "model": "core.auditlog",
    "pk": 1100,
    "fields": {
      "event_id": "281bb183-231a-4b4f-aacf-d730032c8a1c",
      "actor_user": [
        "student1"
      ],
      "action": "user_login",
      "target_table": "users_user",
      "target_id": "5",
      "before": {},
      "after": {},
      "request_id": "",
      "request_path": "",
      "request_method": "",
      "request_status": null,
      "ip_address": "",
      "user_agent": "",
      "metadata": {},
      "previous_hash": "64137574a72fb8b5b1d461d1ff3f60415aab5140a4186caec71e86a255fa2891",
      "integrity_hash": "9a09b832d913777e80a998d727040e08a75c1b7da918313e164c929c4704e0c7",
      "created_at": "2026-03-19T07:18:40.540Z"
    }
  }
]